CHANGELOG
LICENSE
MANIFEST.in
README.rst
buildout.cfg
setup.cfg
setup.py
tangled.session.egg-info/PKG-INFO
tangled.session.egg-info/SOURCES.txt
tangled.session.egg-info/dependency_links.txt
tangled.session.egg-info/requires.txt
tangled.session.egg-info/top_level.txt
tangled/session/__init__.py
tangled/session/flash.py
tangled/session/tests/__init__.py
tangled/session/tests/tests.py