Metadata-Version: 1.1
Name: tangled.session
Version: 0.1a2
Summary: Tangled session integration
Home-page: http://tangledframework.org/
Author: Wyatt Baldwin
Author-email: self@wyattbaldwin.com
License: UNKNOWN
Platform: UNKNOWN
Classifier: Development Status :: 3 - Alpha
Classifier: Intended Audience :: Developers
Classifier: License :: OSI Approved :: MIT License
Classifier: Programming Language :: Python :: 3.3
Classifier: Programming Language :: Python :: 3.4
